{"data" : [{"name" : "아이유", "married" : "N", "birthday" : "19930516", "gender" : "F", "gugun" : "1", "work" : "1", "height" : "161.8", "weight" : "44", "info" : "아이유는 로엔 엔터테인먼트 소속의 대한민국 여성 솔로 가수, 배우이다. 아이유(IU)라는 이름은 ‘I’와 ‘You’를 합친 합성어로 ‘너와 내가 음악으로 하나가 된다’는 의미이다."}, {"name" : "정형돈", "married" : "Y", "birthday" : "19780207", "gender" : "M", "gugun" : "2", "work" : "2,3", "height" : "173", "weight" : "85", "info" : "정형돈은 대한민국의 개그맨이다."}, {"name" : "유승호", "married" : "N", "birthday" : "19930817", "gender" : "M", "gugun" : "3", "work" : "4,5", "height" : "175", "weight" : "55", "info" : "유승호는 대한민국의 배우이다. 1999년 n016 CF로 연예계에 데뷔하였다. 2000년 특집극 《가시고기》로 연기를 시작하였다."}, {"name" : "김민희", "married" : "N", "birthday" : "19820301", "gender" : "F", "gugun" : "4", "work" : "4,5", "height" : "170", "weight" : "49", "info" : "김민희는 대한민국의 탤런트이자 영화배우 모델이다."}, {"name" : "권지용", "married" : "N", "birthday" : "19880818", "gender" : "M", "gugun" : "5", "work" : "1", "height" : "177", "weight" : "58", "info" : "지드래곤은 대한민국의 싱어송라이터이자 프로듀서로, 음악 그룹 빅뱅의 리더이다."}, {"name" : "김현아", "married" : "N", "birthday" : "19920606", "gender" : "F", "gugun" : "6", "work" : "1", "height" : "164", "weight" : "44", "info" : "김현아는 대한민국의 댄스 팝 가수로, 현재는 포미닛의 멤버이다."}, {"name" : "김준현", "married" : "Y", "birthday" : "19801116", "gender" : "M", "gugun" : "7", "work" : "3", "height" : "180", "weight" : "120", "info" : "김준현은 대한민국의 개그맨이다. 본관은 김녕이다. 부친은 前 KBS 교양 PD인 김상근이다."}, {"name" : "송중기", "married" : "N", "birthday" : "19850919", "gender" : "M", "gugun" : "6", "work" : "4,5", "height" : "178", "weight" : "65", "info" : "송중기는 대한민국의 배우이다. 2남 1녀 중 차남으로 대전광역시에서 태어났다. 성균관대학교 경영학과를 졸업하였다. 2008년 영화 《쌍화점》으로 데뷔하였다."}]}